statscollection/__init__.py
statscollection/example/__init__.py
statscollection/example/example.py
statscollection/example/tests/__init__.py
statscollection/online/__init__.py
statscollection/online/abstract_classes.py
statscollection/online/classes.py
statscollection/online/sampling.py
statscollection/online/window_statistics.py
statscollection-0.0.1.dist-info/METADATA
statscollection-0.0.1.dist-info/WHEEL
statscollection-0.0.1.dist-info/top_level.txt
statscollection-0.0.1.dist-info/RECORD
